mlflow_mcp/__init__.py
mlflow_mcp/__main__.py
mlflow_mcp/server.py
mlflow_mcp-0.1.8.dist-info/METADATA
mlflow_mcp-0.1.8.dist-info/WHEEL
mlflow_mcp-0.1.8.dist-info/entry_points.txt
mlflow_mcp-0.1.8.dist-info/licenses/LICENSE
mlflow_mcp-0.1.8.dist-info/RECORD
