Metadata-Version: 2.4
Name: mlflow-mcp
Version: 0.1.8
Summary: A Model Context Protocol (MCP) server for MLflow - enables LLMs to interact with MLflow experiments, runs, metrics, and models
Project-URL: Homepage, https://github.com/kkruglik/mlflow-mcp
Project-URL: Repository, https://github.com/kkruglik/mlflow-mcp
Project-URL: Issues, https://github.com/kkruglik/mlflow-mcp/issues
Author: Kirill Kruglikov
License: MIT
License-File: LICENSE
Keywords: ai,llm,machine-learning,mcp,mlflow,model-context-protocol
Classifier: Development Status :: 4 - Beta
Classifier: Intended Audience :: Developers
Classifier: Intended Audience :: Science/Research
Classifier: License :: OSI Approved :: MIT License
Classifier: Programming Language :: Python :: 3
Classifier: Programming Language :: Python :: 3.10
Classifier: Programming Language :: Python :: 3.11
Classifier: Programming Language :: Python :: 3.12
Classifier: Programming Language :: Python :: 3.13
Classifier: Topic :: Scientific/Engineering :: Artificial Intelligence
Classifier: Topic :: Software Development :: Libraries :: Python Modules
Requires-Python: >=3.10
Requires-Dist: mcp>=1.16.0
Requires-Dist: mlflow>=3.4.0
